Metadata-Version: 1.1
Name: chatterbot-corpus
Version: 1.2.0
Summary: 
